CHANGES.txt
MANIFEST.in
README.txt
setup.cfg
setup.py
DjangoPluggableApp.egg-info/PKG-INFO
DjangoPluggableApp.egg-info/SOURCES.txt
DjangoPluggableApp.egg-info/dependency_links.txt
DjangoPluggableApp.egg-info/entry_points.txt
DjangoPluggableApp.egg-info/not-zip-safe
DjangoPluggableApp.egg-info/requires.txt
DjangoPluggableApp.egg-info/top_level.txt
pluggableapp/__init__.py
pluggableapp/apps.py
pluggableapp/core.py
pluggableapp/scripts.py
pluggableapp/template.py
pluggableapp/templates/app/MANIFEST.in_tmpl
pluggableapp/templates/app/bootstrap.py_tmpl
pluggableapp/templates/app/buildout.cfg_tmpl
pluggableapp/templates/app/setup.cfg_tmpl
pluggableapp/templates/app/setup.py_tmpl
pluggableapp/templates/app/+package+/__init__.py_tmpl
pluggableapp/templates/app/+package+/models.py_tmpl
pluggableapp/templates/app/+package+/urls.py_tmpl
pluggableapp/templates/app/+package+/views.py_tmpl
pluggableapp/templates/app/+package+/media/+package+/README.txt_tmpl
pluggableapp/templates/app/+package+/templates/+package+/base.html_tmpl
pluggableapp/templates/app/+package+/tests/__init__.py_tmpl
pluggableapp/templates/app/+package+/tests/functionnal.py_tmpl
pluggableapp/templates/app/+package+/tests/test_index.py_tmpl
pluggableapp/templates/app/+package+/tests/test_medias.py_tmpl
pluggableapp/templates/app/test_project/__init__.py_tmpl
pluggableapp/templates/app/test_project/settings.py_tmpl
pluggableapp/templates/app/test_project/urls.py_tmpl
pluggableapp/templates/app/test_project/media/README.txt_tmpl
pluggableapp/templates/app/test_project/templates/base.html_tmpl
pluggableapp/templates/project/settings.py_tmpl
pluggableapp/templates/project/media/README.txt_tmpl
pluggableapp/templates/project/templates/404.html_tmpl
pluggableapp/templates/project/templates/500.html_tmpl
pluggableapp/templates/project/templates/base.html_tmpl