Metadata-Version: 1.0
Name: DjangoPluggableApp
Version: 0.5
Summary: A pluggable system for django applications
Home-page: http://packages.python.org/DjangoPluggableApp/
Author: Gael Pasgrimaud
Author-email: gpasgrimaud@bearstech.com
License: BSD
Keywords: django plugin apps
Platform: UNKNOWN
Classifier: Framework :: Django
Classifier: Intended Audience :: Developers
Classifier: License :: OSI Approved :: BSD License
Classifier: Operating System :: POSIX
